{"assets/icons/amazing_views.png":["assets/icons/amazing_views.png"],"assets/icons/beachfront.png":["assets/icons/beachfront.png"],"assets/icons/countryside.png":["assets/icons/countryside.png"],"assets/icons/mansions.png":["assets/icons/mansions.png"],"assets/icons/pools.png":["assets/icons/pools.png"],"assets/images/guide.jpg":["assets/images/guide.jpg"],"assets/images/profile.jpg":["assets/images/profile.jpg"],"assets/images/property1.jpg":["assets/images/property1.jpg"],"assets/images/property1_2.jpg":["assets/images/property1_2.jpg"],"assets/images/property1_3.jpg":["assets/images/property1_3.jpg"],"assets/images/property2.jpg":["assets/images/property2.jpg"],"assets/images/property2_2.jpg":["assets/images/property2_2.jpg"],"assets/images/property2_3.jpg":["assets/images/property2_3.jpg"],"assets/images/property3.jpg":["assets/images/property3.jpg"],"assets/images/property3_2.jpg":["assets/images/property3_2.jpg"],"assets/images/property3_3.jpg":["assets/images/property3_3.jpg"],"assets/images/property4.jpg":["assets/images/property4.jpg"],"assets/images/property4_2.jpg":["assets/images/property4_2.jpg"],"assets/images/property4_3.jpg":["assets/images/property4_3.jpg"],"assets/images/property5.jpg":["assets/images/property5.jpg"],"assets/images/property5_2.jpg":["assets/images/property5_2.jpg"],"assets/images/property5_3.jpg":["assets/images/property5_3.jpg"],"assets/images/support.jpg":["assets/images/support.jpg"],"packages/cupertino_icons/assets/CupertinoIcons.ttf":["packages/cupertino_icons/assets/CupertinoIcons.ttf"]}